setup.py
src/digimat/__init__.py
src/digimat.wink.egg-info/PKG-INFO
src/digimat.wink.egg-info/SOURCES.txt
src/digimat.wink.egg-info/dependency_links.txt
src/digimat.wink.egg-info/namespace_packages.txt
src/digimat.wink.egg-info/not-zip-safe
src/digimat.wink.egg-info/requires.txt
src/digimat.wink.egg-info/top_level.txt
src/digimat/wink/__init__.py
src/digimat/wink/device.py
src/digimat/wink/nimbus.py
src/digimat/wink/wink.py